ampana/__init__.py
ampana/advice.py
ampana/compliment.py
ampana/plan.py
ampana/utils.py
ampana/vibe.py
ampana/weather.py
ampana-0.1.1.dist-info/METADATA
ampana-0.1.1.dist-info/WHEEL
ampana-0.1.1.dist-info/top_level.txt
ampana-0.1.1.dist-info/RECORD
