Metadata-Version: 2.4
Name: ampana
Version: 0.1.1
Summary: A fun Python package that has Vibe.
Requires-Python: >=3.13
Requires-Dist: build>=1.2.2.post1
Requires-Dist: python-dotenv>=1.1.0
Requires-Dist: requests>=2.32.3
Requires-Dist: setuptools>=80.3.1
Requires-Dist: twine>=6.1.0
